nucliadb_client/__init__.py
nucliadb_client/client.py
nucliadb_client/exceptions.py
nucliadb_client/export.py
nucliadb_client/importing.py
nucliadb_client/knowledgebox.py
nucliadb_client/resource.py
nucliadb_client/utils.py
nucliadb_client/tests/__init__.py
nucliadb_client/tests/conftest.py
nucliadb_client/tests/fixtures.py
nucliadb_client/tests/test_export.py
nucliadb_client/tests/test_knowledgebox.py
nucliadb_client/tests/test_resource.py
nucliadb_client-3.0.0.post726.dist-info/METADATA
nucliadb_client-3.0.0.post726.dist-info/WHEEL
nucliadb_client-3.0.0.post726.dist-info/entry_points.txt
nucliadb_client-3.0.0.post726.dist-info/top_level.txt
nucliadb_client-3.0.0.post726.dist-info/zip-safe
nucliadb_client-3.0.0.post726.dist-info/RECORD
