Metadata-Version: 2.1
Name: nucliadb-client
Version: 3.0.0.post726
Home-page: https://nuclia.com
License: BSD
Classifier: Development Status :: 4 - Beta
Classifier: Programming Language :: Python
Classifier: Programming Language :: Python :: 3.9
Classifier: Programming Language :: Python :: 3.10
Classifier: Programming Language :: Python :: 3.11
Classifier: Programming Language :: Python :: 3 :: Only
Classifier: Topic :: Software Development :: Libraries :: Python Modules
Classifier: License :: OSI Approved :: GNU Affero General Public License v3 or later (AGPLv3+)
Requires-Python: >=3.8, <4
Requires-Dist: httpx
Requires-Dist: protobuf >=3.19.3
Requires-Dist: types-protobuf <4.0,>=3.19.5
Requires-Dist: grpcio >=1.44.0
Requires-Dist: aiofiles
Requires-Dist: nucliadb-protos >=2.24.0
Requires-Dist: nucliadb-models >=2.24.0
Requires-Dist: nucliadb-telemetry >=1.15.0
Requires-Dist: urllib3 <1.27,>=1.21.1
